qbstreamlit/__init__.py
qbstreamlit/charts.py
qbstreamlit/data.py
qbstreamlit/parser.py
qbstreamlit/tables.py
qbstreamlit/utils.py
qbstreamlit-0.1.0.dist-info/LICENSE
qbstreamlit-0.1.0.dist-info/METADATA
qbstreamlit-0.1.0.dist-info/WHEEL
qbstreamlit-0.1.0.dist-info/top_level.txt
qbstreamlit-0.1.0.dist-info/RECORD
